nmbu/__init__.py
nmbu/rinex/__init__.py
nmbu/rinex/reader.py
nmbu/rinex/common/__init__.py
nmbu/rinex/common/rinex_data.py
nmbu/rinex/navigation/__init__.py
nmbu/rinex/navigation/v3/__init__.py
nmbu/rinex/navigation/v3/header.py
nmbu/rinex/navigation/v3/navigation.py
nmbu/rinex/navigation/v3/nav_message_type/BDS.py
nmbu/rinex/navigation/v3/nav_message_type/GAL.py
nmbu/rinex/navigation/v3/nav_message_type/GLOv3_04.py
nmbu/rinex/navigation/v3/nav_message_type/GLOv3_05.py
nmbu/rinex/navigation/v3/nav_message_type/GPS.py
nmbu/rinex/navigation/v3/nav_message_type/IRN.py
nmbu/rinex/navigation/v3/nav_message_type/QZS.py
nmbu/rinex/navigation/v3/nav_message_type/SBAS.py
nmbu/rinex/navigation/v3/nav_message_type/__init__.py
nmbu/rinex/navigation/v4/__init__.py
nmbu/rinex/navigation/v4/header.py
nmbu/rinex/navigation/v4/navigation.py
nmbu/rinex/navigation/v4/nav_message_type/BDS_CNAV1.py
nmbu/rinex/navigation/v4/nav_message_type/BDS_CNAV2.py
nmbu/rinex/navigation/v4/nav_message_type/BDS_CNAV3.py
nmbu/rinex/navigation/v4/nav_message_type/BDS_D1_D2.py
nmbu/rinex/navigation/v4/nav_message_type/EOP.py
nmbu/rinex/navigation/v4/nav_message_type/GAL_INAV_FNAV.py
nmbu/rinex/navigation/v4/nav_message_type/GLO_FDMA.py
nmbu/rinex/navigation/v4/nav_message_type/GPS_CNAV.py
nmbu/rinex/navigation/v4/nav_message_type/GPS_CNAV2.py
nmbu/rinex/navigation/v4/nav_message_type/GPS_LNAV.py
nmbu/rinex/navigation/v4/nav_message_type/ION_BDGIM.py
nmbu/rinex/navigation/v4/nav_message_type/ION_Klobuchar.py
nmbu/rinex/navigation/v4/nav_message_type/ION_Nequick.py
nmbu/rinex/navigation/v4/nav_message_type/IRN_LNAV.py
nmbu/rinex/navigation/v4/nav_message_type/QZS_CNAV.py
nmbu/rinex/navigation/v4/nav_message_type/QZS_CNAV2.py
nmbu/rinex/navigation/v4/nav_message_type/QZS_LNAV.py
nmbu/rinex/navigation/v4/nav_message_type/SBAS.py
nmbu/rinex/navigation/v4/nav_message_type/STO.py
nmbu/rinex/navigation/v4/nav_message_type/__init__.py
nmbu/rinex/observation/__init__.py
nmbu/rinex/observation/v3/__init__.py
nmbu.rinex-1.0.1.dist-info/COPYING
nmbu.rinex-1.0.1.dist-info/METADATA
nmbu.rinex-1.0.1.dist-info/WHEEL
nmbu.rinex-1.0.1.dist-info/top_level.txt
nmbu.rinex-1.0.1.dist-info/RECORD
