Metadata-Version: 2.1
Name: nmbu.rinex
Version: 1.0.1
Summary: Reader for RINEX v3 and v4 formats for both observation and navigation files
Author: Liudmila Sherstnyakova
Project-URL: Homepage, https://github.com/liudmila-sherstnyakova/rinex-reader
Project-URL: Bug Tracker, https://github.com/liudmila-sherstnyakova/rinex-reader/issues
Classifier: Programming Language :: Python :: 3
Classifier: License :: OSI Approved :: GNU General Public License v3 or later (GPLv3+)
Classifier: Operating System :: OS Independent
Requires-Python: >=3.8
License-File: COPYING
